Workbook

Sheet Artikelauswertung
A1: Inventur zum 31.12.2024
A3: Nr | B3: Beschreibung | C3: Beschreibung 2 | D3: Produktgruppencode | E3: Inventurgruppencode | F3: Lagerort | G3: Bestand Datum | H3: Basiseinheit | I3: Nettogewicht kg/ Einheit | J3: Nettogewicht kg | K3: Bewertungspreis € / Einheit | L3: Bewertungspreis €
A4: H063 | B4: Europaletten | D4: 807 | E4: Fertigwaren | F4: HAUPT | G4: 35911 | H4: STÜCK | I4: 20 | J4: =G4*I4 -> 718220 | K4: 7.67 | L4: =G4*K4 -> 275437.37
A5: 81222012 | B5: Lilys Kitchen Dog Chicken & Duck | C5: Countryside Casserole Adult Dry Food - Indu | D5: 510 | E5: Fertigwaren | F5: HAUPT | G5: 18316 | H5: STÜCK | I5: 12 | J5: =G5*I5 -> 219792 | K5: 17.7922 | L5: =G5*K5 -> 325881.94
A6: 5462012 | B6: Canagan Free-Range Chicken For Dogs | D6: 510 | E6: Fertigwaren | F6: HAUPT | G6: 15392 | H6: STÜCK | I6: 12 | J6: =G6*I6 -> 184704 | K6: 14.4104 | L6: =G6*K6 -> 221804.88
A7: 8005125 | B7: Wolfsblut Wild Duck Adult | D7: 510 | E7: Fertigwaren | F7: HAUPT | G7: 11052 | H7: STÜCK | I7: 12.5 | J7: =G7*I7 -> 138150 | K7: 16.532 | L7: =G7*K7 -> 182711.66
A8: 81212012 | B8: Lilys Kitchen Dog Lamb | C8: Shepherds Pie Adult Dry Food - Indu | D8: 510 | E8: Fertigwaren | F8: HAUPT | G8: 7258 | H8: STÜCK | I8: 12 | J8: =G8*I8 -> 87096 | K8: 22.7752 | L8: =G8*K8 -> 165302.4
A9: 5735012 | B9: Canagan Grass Fed Lamb For Dogs | D9: 510 | E9: Fertigwaren | F9: HAUPT | G9: 5728 | H9: STÜCK | I9: 12 | J9: =G9*I9 -> 68736 | K9: 28.3642 | L9: =G9*K9 -> 162470.14
A10: 8004125 | B10: Wolfsblut Adult Wide Plain Horse | D10: 510 | E10: Fertigwaren | F10: HAUPT | G10: 4927 | H10: STÜCK | I10: 12.5 | J10: =G10*I10 -> 61587.5 | K10: 29.6931 | L10: =G10*K10 -> 146297.9
A11: 8338012 | B11: Sanabelle Adult Geflügel | D11: 503 | E11: Fertigwaren | F11: HAUPT | G11: 7455 | H11: STÜCK | I11: 12 | J11: =G11*I11 -> 89460 | K11: 16.9252 | L11: =G11*K11 -> 126177.37
A12: 53120012 | B12: Briantos Prive Soft Adult Lachs & Kartoffel LA | D12: 510 | E12: Fertigwaren | F12: HAUPT | G12: 9790 | H12: STÜCK | I12: 12 | J12: =G12*I12 -> 117480 | K12: 12.7742 | L12: =G12*K12 -> 125059.42
A13: 8053125 | B13: Wolfsblut Dark Forest Adult | D13: 510 | E13: Fertigwaren | F13: HAUPT | G13: 5952 | H13: STÜCK | I13: 12.5 | J13: =G13*I13 -> 74400 | K13: 20.8038 | L13: =G13*K13 -> 123824.22
A14: 81242012 | B14: Lilys Kitchen Dog Duck, Salmon & Venison | C14: Wild Woodland Walk Adult Dry Food - Indu | D14: 510 | E14: Fertigwaren | F14: HAUPT | G14: 6015 | H14: STÜCK | I14: 12 | J14: =G14*I14 -> 72180 | K14: 19.9562 | L14: =G14*K14 -> 120036.54
A15: 5472012 | B15: Canagan Scottish Salmon For Dogs | D15: 510 | E15: Fertigwaren | F15: HAUPT | G15: 5980 | H15: STÜCK | I15: 12 | J15: =G15*I15 -> 71760 | K15: 19.2522 | L15: =G15*K15 -> 115128.16
A16: 52010015 | B16: Junior Lamm & Reis | D16: 502 | E16: Fertigwaren | F16: HAUPT | G16: 7538 | H16: STÜCK | I16: 15 | J16: =G16*I16 -> 113070 | K16: 15.2069 | L16: =G16*K16 -> 114629.61
A17: 51963010 | B17: K-Classic Kroketten mit Rind & Gemüse | C17: Kaufland (OE) - Relaunch | D17: 510 | E17: Fertigwaren | F17: HAUPT | G17: 34964 | H17: STÜCK | I17: 10 | J17: =G17*I17 -> 349640 | K17: 3.2257 | L17: =G17*K17 -> 112783.37
A18: 56140012 | B18: Edgard & Cooper Dog Export Dry Lamb | D18: 510 | E18: Fertigwaren | F18: HAUPT | G18: 5171 | H18: STÜCK | I18: 12 | J18: =G18*I18 -> 62052 | K18: 21.3324 | L18: =G18*K18 -> 110309.84
A19: 51482012 | B19: Wildkind RED CANYON | D19: 510 | E19: Fertigwaren | F19: HAUPT | G19: 3720 | H19: STÜCK | I19: 12 | J19: =G19*I19 -> 44640 | K19: 26.3139 | L19: =G19*K19 -> 97887.708
A20: 52160125 | B20: Senior | D20: 502 | E20: Fertigwaren | F20: HAUPT | G20: 12311 | H20: STÜCK | I20: 12.5 | J20: =G20*I20 -> 153887.5 | K20: 7.8355 | L20: =G20*K20 -> 96462.84
A21: 57570125 | B21: HPC SOFT Maxi Wasserbüffel & Süßkartoffel | D21: 519 | E21: Fertigwaren | F21: HAUPT | G21: 3920 | H21: STÜCK | I21: 12.5 | J21: =G21*I21 -> 49000 | K21: 24.593 | L21: =G21*K21 -> 96404.56
A22: 548614 | B22: Tales u Tails Soft Ente & Gemüse | D22: 510 | E22: Fertigwaren | F22: BRUCKER_2 | G22: 14832 | H22: STÜCK | I22: 4 | J22: =G22*I22 -> 59328 | K22: 6.4287 | L22: =G22*K22 -> 95350.478
A23: 5465012 | B23: Canagan Large Breed Free-Range Chicken For Dogs | D23: 510 | E23: Fertigwaren | F23: HAUPT | G23: 6576 | H23: STÜCK | I23: 12 | J23: =G23*I23 -> 78912 | K23: 14.3893 | L23: =G23*K23 -> 94624.037
A24: 5726012 | B24: Canagan Country Game For Dogs | D24: 510 | E24: Fertigwaren | F24: HAUPT | G24: 5300 | H24: STÜCK | I24: 12 | J24: =G24*I24 -> 63600 | K24: 17.2894 | L24: =G24*K24 -> 91633.82
A25: 5211 | B25: HPC Active Relaunch | C25: braunes mittelgroßes Viereck | D25: 853 | E25: Monokroketten | F25: HAUPT | G25: 100696.5 | H25: KG | I25: 1 | J25: =G25*I25 -> 100696.5 | K25: 0.5794 | L25: =G25*K25 -> 58343.552
A26: 5462006 | B26: Canagan Free-Range Chicken For Dogs | D26: 510 | E26: Fertigwaren | F26: HAUPT | G26: 12716 | H26: STÜCK | I26: 6 | J26: =G26*I26 -> 76296 | K26: 7.2052 | L26: =G26*K26 -> 91621.323
A27: 5466012 | B27: Canagan Light / Senior For Dogs | D27: 510 | E27: Fertigwaren | F27: HAUPT | G27: 6221 | H27: STÜCK | I27: 12 | J27: =G27*I27 -> 74652 | K27: 14.5728 | L27: =G27*K27 -> 90657.389
A28: 52080015 | B28: Adult Lamm & Reis | D28: 502 | E28: Fertigwaren | F28: HAUPT | G28: 9101 | H28: STÜCK | I28: 15 | J28: =G28*I28 -> 136515 | K28: 9.9609 | L28: =G28*K28 -> 90654.151
A29: 8124207 | B29: Lilys Kitchen Dog Duck, Salmon & Venison | C29: Wild Woodland Walk Adult Dry food - Indu | D29: 510 | E29: Fertigwaren | F29: HAUPT | G29: 7668 | H29: STÜCK | I29: 7 | J29: =G29*I29 -> 53676 | K29: 11.6722 | L29: =G29*K29 -> 89502.43
A30: 56150012 | B30: Edgard & Cooper Dog Export Dry Vension & Duck | D30: 510 | E30: Fertigwaren | F30: HAUPT | G30: 5032 | H30: STÜCK | I30: 12 | J30: =G30*I30 -> 60384 | K30: 16.7111 | L30: =G30*K30 -> 84090.255
A31: 850004 | B31: Tales u Tails Soft Pferd | D31: 510 | E31: Fertigwaren | F31: BRUCKER_2 | G31: 6048 | H31: STÜCK | I31: 4 | J31: =G31*I31 -> 24192 | K31: 13.7269 | L31: =G31*K31 -> 83020.291
A32: 57142015 | B32: Orlando Gourmet Hundetrockenfutter SK4 | C32: RO/HR/BG/GR,CY/RS | D32: 510 | E32: Fertigwaren | F32: HAUPT | G32: 101490 | H32: STÜCK | I32: 1.5 | J32: =G32*I32 -> 152235 | K32: 0.8171 | L32: =G32*K32 -> 82927.479
A33: 557714 | B33: Tales u Tails Soft Lamm | D33: 510 | E33: Fertigwaren | F33: BRUCKER_2 | G33: 6408 | H33: STÜCK | I33: 4 | J33: =G33*I33 -> 25632 | K33: 12.9014 | L33: =G33*K33 -> 82672.171
A34: 81212025 | B34: Lilys Kitchen Dog Lamb | C34: Shepherds Pie Adult Dry Food - Indu | D34: 510 | E34: Fertigwaren | F34: HAUPT | G34: 16064 | H34: STÜCK | I34: 2.5 | J34: =G34*I34 -> 40160 | K34: 5.0142 | L34: =G34*K34 -> 80548.109
A35: 83460010 | B35: Sanabelle Sterilized | D35: 503 | E35: Fertigwaren | F35: HAUPT | G35: 5685 | H35: STÜCK | I35: 10 | J35: =G35*I35 -> 56850 | K35: 14.1381 | L35: =G35*K35 -> 80375.098
A36: 5424107 | B36: HeyHoly Kleine Doggen | C36: Beautiful Bulldogs | D36: 510 | E36: Fertigwaren | F36: HAUPT | G36: 8710 | H36: STÜCK | I36: 7 | J36: =G36*I36 -> 60970 | K36: 9.1977 | L36: =G36*K36 -> 80111.967
A37: 8122201 | B37: Lilys Kitchen Dog Chicken & Duck | C37: Countryside Casserole Adult Dry Food - Indu | D37: 510 | E37: Fertigwaren | F37: HAUPT | G37: 45360 | H37: STÜCK | I37: 1 | J37: =G37*I37 -> 45360 | K37: 1.7129 | L37: =G37*K37 -> 77697.144
A38: 8336 | B38: Sanabelle Sensitiv Geflügel Relaunch 2018 | C38: Dunkelbraune kleine Scheibe | D38: 853 | E38: Monokroketten | F38: HAUPT | G38: 22908 | H38: KG | I38: 1 | J38: =G38*I38 -> 22908 | K38: 1.2424 | L38: =G38*K38 -> 28460.899
A39: 7979 | B39: Ex.Dog rotes geriffeltes Ei 4 % Rind 4 % Erbsen | C39: rotes großes geriffeltes Ei | D39: 851 | E39: Extrudate | F39: HAUPT | G39: 123115.94 | H39: KG | I39: 1 | J39: =G39*I39 -> 123115.94 | K39: 0.2396 | L39: =G39*K39 -> 29498.579
A40: 5233102 | B40: 4 Paws Softbrocken mit Huhn | D40: 510 | E40: Fertigwaren | F40: HAUPT | G40: 33696 | H40: STÜCK | I40: 2 | J40: =G40*I40 -> 67392 | K40: 2.3018 | L40: =G40*K40 -> 77561.453
A41: 53110012 | B41: Briantos Prive Soft Adult Ente & Kartoffel LA | D41: 510 | E41: Fertigwaren | F41: HAUPT | G41: 6749 | H41: STÜCK | I41: 12 | J41: =G41*I41 -> 80988 | K41: 11.2575 | L41: =G41*K41 -> 75976.868
A42: 53211603 | B42: Pablo Kraft Nahrung | C42: reich an Geflügel mit Hirse | D42: 510 | E42: Fertigwaren | F42: HAUPT | G42: 50304 | H42: STÜCK | I42: 3 | J42: =G42*I42 -> 150912 | K42: 1.5038 | L42: =G42*K42 -> 75647.155
A43: 563014 | B43: Tales u Tails Soft Forelle & Hering | C43: Forelle & Hering | D43: 510 | E43: Fertigwaren | F43: BRUCKER_2 | G43: 8208 | H43: STÜCK | I43: 4 | J43: =G43*I43 -> 32832 | K43: 9.1113 | L43: =G43*K43 -> 74785.55
A44: 52646010 | B44: Gut & Günstig Lieblingsmenü | C44: mit Huhn, Gemüse, Hirse und Lammgeschmack | D44: 510 | E44: Fertigwaren | F44: HAUPT | G44: 21136 | H44: STÜCK | I44: 10 | J44: =G44*I44 -> 211360 | K44: 3.538 | L44: =G44*K44 -> 74779.168
A45: 83360010 | B45: Sanabelle Sensitive Geflügel | D45: 503 | E45: Fertigwaren | F45: HAUPT | G45: 5095 | H45: STÜCK | I45: 10 | J45: =G45*I45 -> 50950 | K45: 14.6766 | L45: =G45*K45 -> 74777.277
A46: 56180112 | B46: Rinti KF MAX-I-MUM Huhn | C46: ohne Säurekombination / hochgepackt | D46: 510 | E46: Fertigwaren | F46: HAUPT | G46: 5553 | H46: STÜCK | I46: 12 | J46: =G46*I46 -> 66636 | K46: 13.3575 | L46: =G46*K46 -> 74174.197
A47: 54850110 | B47: K-Classic Kroketten mit Lamm & Hirse | C47: Kaufland (OE) - Relaunch | D47: 510 | E47: Fertigwaren | F47: HAUPT | G47: 21990 | H47: STÜCK | I47: 10 | J47: =G47*I47 -> 219900 | K47: 3.3642 | L47: =G47*K47 -> 73978.758
A48: 52070015 | B48: Adult Geflügel & Hirse | D48: 502 | E48: Fertigwaren | F48: HAUPT | G48: 7071 | H48: STÜCK | I48: 15 | J48: =G48*I48 -> 106065 | K48: 10.0763 | L48: =G48*K48 -> 71249.517
A49: 52050015 | B49: Mini Adult Lamm & Reis | D49: 502 | E49: Fertigwaren | F49: HAUPT | G49: 5762 | H49: STÜCK | I49: 15 | J49: =G49*I49 -> 86430 | K49: 12.2635 | L49: =G49*K49 -> 70662.287
A50: 5723102 | B50: Cachet Classic | C50: 2x Rind / 2x MSC Lachs - Aldi PT - MSC-C-55377 | D50: 511 | E50: Fertigwaren | F50: LEINWE_ROT | G50: 65088 | H50: STÜCK | I50: 2 | J50: =G50*I50 -> 130176 | K50: 1.0765 | L50: =G50*K50 -> 70067.232
A51: 5201 | B51: HPC Junior Lamm & Reis Relaunch Kolostrum | C51: braune mittelgroße Scheibe | D51: 853 | E51: Monokroketten | F51: HAUPT | G51: 21005.3 | H51: KG | I51: 1 | J51: =G51*I51 -> 21005.3 | K51: 0.8785 | L51: =G51*K51 -> 18453.156
A52: 83310012 | B52: Sanabelle Adult Strauß | C52: Overfiller 10 + 2 kg | D52: 503 | E52: Fertigwaren | F52: HAUPT | G52: 3705 | H52: STÜCK | I52: 12 | J52: =G52*I52 -> 44460 | K52: 18.5224 | L52: =G52*K52 -> 68625.492
A53: 52100015 | B53: Maxi Adult | D53: 502 | E53: Fertigwaren | F53: HAUPT | G53: 8179 | H53: STÜCK | I53: 15 | J53: =G53*I53 -> 122685 | K53: 8.3818 | L53: =G53*K53 -> 68554.742
A54: 56754015 | B54: VIVAPET Krox | C54: 2023 | D54: 510 | E54: Fertigwaren | F54: LEINWE_ROT | G54: 15024 | H54: STÜCK | I54: 15 | J54: =G54*I54 -> 225360 | K54: 4.5374 | L54: =G54*K54 -> 68169.898
A55: 574004 | B55: Tales u Tails Soft Insekten | D55: 510 | E55: Fertigwaren | F55: BRUCKER_2 | G55: 6336 | H55: STÜCK | I55: 4 | J55: =G55*I55 -> 25344 | K55: 10.7278 | L55: =G55*K55 -> 67971.341
A56: 5732006 | B56: Canagan Small Breed Scottish Salmon for Dogs | D56: 510 | E56: Fertigwaren | F56: HAUPT | G56: 7040 | H56: STÜCK | I56: 6 | J56: =G56*I56 -> 42240 | K56: 9.6261 | L56: =G56*K56 -> 67767.744
A57: 8359007 | B57: Edgard & Cooper Dog Export Dry Lamb | D57: 510 | E57: Fertigwaren | F57: HAUPT | G57: 5354 | H57: STÜCK | I57: 7 | J57: =G57*I57 -> 37478 | K57: 12.4436 | L57: =G57*K57 -> 66623.034
A58: 8122207 | B58: Lilys Kitchen Dog Chicken & Duck | C58: Countryside Casserole Adult Dry Food - Indu | D58: 510 | E58: Fertigwaren | F58: HAUPT | G58: 6156 | H58: STÜCK | I58: 7 | J58: =G58*I58 -> 43092 | K58: 10.7732 | L58: =G58*K58 -> 66319.819
A59: 51090015 | B59: deuka Sensikost | D59: 510 | E59: Fertigwaren | F59: LEINWE_ROT | G59: 4719 | H59: STÜCK | I59: 15 | J59: =G59*I59 -> 70785 | K59: 13.8253 | L59: =G59*K59 -> 65241.591
A60: 8799008 | B60: Cachet Premium Sortiment | C60: Aldi Nord - MSC-C-55377 | D60: 511 | E60: Fertigwaren | F60: LEINWE_ROT | G60: 66600 | H60: STÜCK | I60: 0.8 | J60: =G60*I60 -> 53280 | K60: 0.9764 | L60: =G60*K60 -> 65028.24
A61: 5725012 | B61: Canagan Highland Feast for Dogs | D61: 510 | E61: Fertigwaren | F61: HAUPT | G61: 3615 | H61: STÜCK | I61: 12 | J61: =G61*I61 -> 43380 | K61: 17.725 | L61: =G61*K61 -> 64075.875
A62: 53600125 | B62: HPC PLUS Adult Strauß & Kartoffel | D62: 519 | E62: Fertigwaren | F62: HAUPT | G62: 4032 | H62: STÜCK | I62: 12.5 | J62: =G62*I62 -> 50400 | K62: 15.8481 | L62: =G62*K62 -> 63899.539
A63: H0636 | B63: Einweg Europaletten | D63: 807 | E63: Fertigwaren | F63: HAUPT | G63: 0 | H63: STÜCK | I63: 20 | J63: =G63*I63 -> 0 | K63: 7.67 | L63: =G63*K63 -> 0
A64: 85310012 | B64: Multifit Junior Maxi | C64: 2024 | D64: 510 | E64: Fertigwaren | F64: LEINWE_ROT | G64: 10044 | H64: STÜCK | I64: 12 | J64: =G64*I64 -> 120528 | K64: 6.1922 | L64: =G64*K64 -> 62194.457
A65: 53420012 | B65: Rocco Rind | D65: 510 | E65: Fertigwaren | F65: HAUPT | G65: 3754 | H65: STÜCK | I65: 12 | J65: =G65*I65 -> 45048 | K65: 16.3942 | L65: =G65*K65 -> 61543.827
A66: 5735006 | B66: Canagan Grass Fed Lamb For Dogs | D66: 510 | E66: Fertigwaren | F66: HAUPT | G66: 3946 | H66: STÜCK | I66: 6 | J66: =G66*I66 -> 23676 | K66: 15.4714 | L66: =G66*K66 -> 61050.144
A67: 52140125 | B67: Light | D67: 502 | E67: Fertigwaren | F67: HAUPT | G67: 8069 | H67: STÜCK | I67: 12.5 | J67: =G67*I67 -> 100862.5 | K67: 7.533 | L67: =G67*K67 -> 60783.777
A68: 52090015 | B68: Adult Lachs & Kartoffel | D68: 502 | E68: Fertigwaren | F68: HAUPT | G68: 5228 | H68: STÜCK | I68: 15 | J68: =G68*I68 -> 78420 | K68: 11.6076 | L68: =G68*K68 -> 60684.533
A69: 8159125 | B69: Wolfsblut Down Under | D69: 510 | E69: Fertigwaren | F69: HAUPT | G69: 2510 | H69: STÜCK | I69: 12.5 | J69: =G69*I69 -> 31375 | K69: 23.991 | L69: =G69*K69 -> 60217.41
A70: 52190015 | B70: Sensitive Lamm & Reis | D70: 502 | E70: Fertigwaren | F70: HAUPT | G70: 4215 | H70: STÜCK | I70: 15 | J70: =G70*I70 -> 63225 | K70: 14.2508 | L70: =G70*K70 -> 60067.122
A71: 5716102 | B71: Shah Classic Sortiment Katzentrockenfutter | D71: 511 | E71: Fertigwaren | F71: HAUPT | G71: 61584 | H71: STÜCK | I71: 2 | J71: =G71*I71 -> 123168 | K71: 0.9603 | L71: =G71*K71 -> 59139.115
A72: 5464006 | B72: Canagan Small Breed Free-Range Chicken For Dogs | D72: 510 | E72: Fertigwaren | F72: HAUPT | G72: 8115 | H72: STÜCK | I72: 6 | J72: =G72*I72 -> 48690 | K72: 7.1425 | L72: =G72*K72 -> 57961.387
A73: 5708003 | B73: Orlando Hundetrockenfutter Nuggets SK1 | C73: PL | D73: 510 | E73: Fertigwaren | F73: HAUPT | G73: 44928 | H73: STÜCK | I73: 3 | J73: =G73*I73 -> 134784 | K73: 1.2771 | L73: =G73*K73 -> 57377.549
A74: 5716202 | B74: Attica Knusprige Mischung Sortiment | C74: mit Huhn & mit Rind | D74: 511 | E74: Fertigwaren | F74: HAUPT | G74: 59741 | H74: STÜCK | I74: 2 | J74: =G74*I74 -> 119482 | K74: 0.9546 | L74: =G74*K74 -> 57028.759
A75: 8072125 | B75: Wolfsblut Black Bird Adult | D75: 510 | E75: Fertigwaren | F75: HAUPT | G75: 3600 | H75: STÜCK | I75: 12.5 | J75: =G75*I75 -> 45000 | K75: 15.8194 | L75: =G75*K75 -> 56949.84
A76: 50700125 | B76: HPC SOFT Adult Hühnchen & Banane | D76: 519 | E76: Fertigwaren | F76: HAUPT | G76: 3206 | H76: STÜCK | I76: 12.5 | J76: =G76*I76 -> 40075 | K76: 17.6313 | L76: =G76*K76 -> 56525.948
A77: 83350010 | B77: Sanabelle Adult Forelle | D77: 503 | E77: Fertigwaren | F77: HAUPT | G77: 4029 | H77: STÜCK | I77: 10 | J77: =G77*I77 -> 40290 | K77: 13.9547 | L77: =G77*K77 -> 56223.486
A78: 83480010 | B78: Sanabelle Senior | D78: 503 | E78: Fertigwaren | F78: HAUPT | G78: 3804 | H78: STÜCK | I78: 10 | J78: =G78*I78 -> 38040 | K78: 14.3639 | L78: =G78*K78 -> 54640.276
A79: 85300012 | B79: Multifit Junior | C79: 2024 | D79: 510 | E79: Fertigwaren | F79: LEINWE_ROT | G79: 8316 | H79: STÜCK | I79: 12 | J79: =G79*I79 -> 99792 | K79: 6.5019 | L79: =G79*K79 -> 54069.8
A80: 5464002 | B80: Canagan Small Breed Free-Range Chicken For Dogs | D80: 510 | E80: Fertigwaren | F80: HAUPT | G80: 21381 | H80: STÜCK | I80: 2 | J80: =G80*I80 -> 42762 | K80: 2.5132 | L80: =G80*K80 -> 53734.729
A81: 8107004 | B81: Premiere Soft Adult Rind | D81: 510 | E81: Fertigwaren | F81: LEINWE_ROT | G81: 10080 | H81: STÜCK | I81: 4 | J81: =G81*I81 -> 40320 | K81: 5.302 | L81: =G81*K81 -> 53444.16
A82: 8357007 | B82: Edgard & Cooper Dog Export Dry Salmon | D82: 510 | E82: Fertigwaren | F82: HAUPT | G82: 6216 | H82: STÜCK | I82: 7 | J82: =G82*I82 -> 43512 | K82: 8.4928 | L82: =G82*K82 -> 52791.245
A83: 56110012 | B83: Edgard & Cooper Dog Export Dry Salmon | D83: 510 | E83: Fertigwaren | F83: HAUPT | G83: 3645 | H83: STÜCK | I83: 12 | J83: =G83*I83 -> 43740 | K83: 14.442 | L83: =G83*K83 -> 52641.09
A84: 5757025 | B84: HPC SOFT Maxi Wasserbüffel & Süßkartoffel | D84: 519 | E84: Fertigwaren | F84: HAUPT | G84: 9882 | H84: STÜCK | I84: 2.5 | J84: =G84*I84 -> 24705 | K84: 5.2975 | L84: =G84*K84 -> 52349.895
A85: 5732102 | B85: Canagan Small Breed Salmon (Japan) | C85: Japanese | D85: 510 | E85: Fertigwaren | F85: HAUPT | G85: 15751 | H85: STÜCK | I85: 2 | J85: =G85*I85 -> 31502 | K85: 3.3193 | L85: =G85*K85 -> 52282.294
A86: 83390010 | B86: Sanabelle No Grain | D86: 503 | E86: Fertigwaren | F86: HAUPT | G86: 3307 | H86: STÜCK | I86: 10 | J86: =G86*I86 -> 33070 | K86: 15.744 | L86: =G86*K86 -> 52065.408
A87: 5471008 | B87: Canagan Free-Range Chicken For Cats | D87: 511 | E87: Fertigwaren | F87: HAUPT | G87: 4559 | H87: STÜCK | I87: 8 | J87: =G87*I87 -> 36472 | K87: 11.4057 | L87: =G87*K87 -> 51998.586
A88: 8358001 | B88: Edgard & Cooper dog Chicken Adult | C88: Edgard & Cooper Croq. au poulet frais | D88: 510 | E88: Fertigwaren | F88: HAUPT | G88: 45576 | H88: STÜCK | I88: 1 | J88: =G88*I88 -> 45576 | K88: 1.139 | L88: =G88*K88 -> 51911.064
A89: 53162015 | B89: Pablo Saftige Happen | D89: 510 | E89: Fertigwaren | F89: HAUPT | G89: 63710 | H89: STÜCK | I89: 1.5 | J89: =G89*I89 -> 95565 | K89: 0.8103 | L89: =G89*K89 -> 51624.213
A90: 5170002 | B90: Gut & Günstig Knuspermenü mit Rind | D90: 511 | E90: Fertigwaren | F90: HAUPT | G90: 53856 | H90: STÜCK | I90: 2 | J90: =G90*I90 -> 107712 | K90: 0.9478 | L90: =G90*K90 -> 51044.717
A91: 932220 | B91: My Friend | D91: 505 | E91: Fertigwaren | F91: HAUPT | G91: 8882 | H91: STÜCK | I91: 20 | J91: =G91*I91 -> 177640 | K91: 5.7391 | L91: =G91*K91 -> 50974.686
A92: 8370015 | B92: MaxiDog Dynamic- (Offiziell ERGÄNZUNGSFUTTER) | D92: 510 | E92: Fertigwaren | F92: HAUPT | G92: 2592 | H92: STÜCK | I92: 15 | J92: =G92*I92 -> 38880 | K92: 19.437 | L92: =G92*K92 -> 50380.704
A93: 5209 | B93: HPC Adult Lachs & Kartoffel Kolostrum | C93: brauner großer Fisch&braunes mittelgroßes Dreieck | D93: 853 | E93: Monokroketten | F93: HAUPT | G93: 22356.56 | H93: KG | I93: 1 | J93: =G93*I93 -> 22356.56 | K93: 0.646 | L93: =G93*K93 -> 14442.338
A94: 5732002 | B94: Canagan Small Breed Scottish Salmon for Dogs | D94: 510 | E94: Fertigwaren | F94: HAUPT | G94: 14808 | H94: STÜCK | I94: 2 | J94: =G94*I94 -> 29616 | K94: 3.341 | L94: =G94*K94 -> 49473.528
A95: 83380010 | B95: Sanabelle Adult Geflügel | D95: 503 | E95: Fertigwaren | F95: HAUPT | G95: 3549 | H95: STÜCK | I95: 10 | J95: =G95*I95 -> 35490 | K95: 13.9019 | L95: =G95*K95 -> 49337.843
A96: H0633 | B96: Europaletten Defekt | C96: (14 defekte pro Stellplatz) gestretcht | D96: 807 | E96: Fertigwaren | F96: HAUPT | G96: 960 | H96: STÜCK | I96: 23 | J96: =G96*I96 -> 22080 | K96: 7.67 | L96: =G96*K96 -> 7363.2
A97: 8348 | B97: Sanabelle Senior Relaunch 2018 | C97: Braune kleine Scheibe | D97: 853 | E97: Monokroketten | F97: HAUPT | G97: 10201 | H97: KG | I97: 1 | J97: =G97*I97 -> 10201 | K97: 1.1747 | L97: =G97*K97 -> 11983.115
A98: 5731006 | B98: Canagan Small Breed Country Game For Dogs | D98: 510 | E98: Fertigwaren | F98: HAUPT | G98: 5656 | H98: STÜCK | I98: 6 | J98: =G98*I98 -> 33936 | K98: 8.6447 | L98: =G98*K98 -> 48894.423
A99: 5471004 | B99: Canagan Free-Range Chicken For Cats | D99: 511 | E99: Fertigwaren | F99: HAUPT | G99: 8160 | H99: STÜCK | I99: 4 | J99: =G99*I99 -> 32640 | K99: 5.9733 | L99: =G99*K99 -> 48742.128
A100: 8062003 | B100: Wolfsblut Wildcat Bhadra Adult | D100: 511 | E100: Fertigwaren | F100: BRUCKER_AA | G100: 4608 | H100: STÜCK | I100: 3 | J100: =G100*I100 -> 13824 | K100: 10.5142 | L100: =G100*K100 -> 48449.434
A101: 80371012 | B101: Wolf of Wilderness Soft Pure Adult Lachs 1.0 | C101: 2022 | D101: 510 | E101: Fertigwaren | F101: HAUPT | G101: 2829 | H101: STÜCK | I101: 12 | J101: =G101*I101 -> 33948 | K101: 17.1205 | L101: =G101*K101 -> 48433.895
...

Sheet Kategorien Summen
B2: 2024
A3: Zeilenbeschriftungen | B3: Summe von Nettogewicht kg | C3: Summe von Bewertungspreis € | D3: Summen
A4: Ersatzteile | B4: =SUMIF(Artikelauswertung!$E$4:$E$12118,'Kategorien Summen'!A4,Artikelauswertung!$J$4:$J$12118) -> 2043836.1 | C4: =SUMIF(Artikelauswertung!$E$4:$E$12118,'Kategorien Summen'!A4,Artikelauswertung!$L$4:$L$12118) -> 10079558 | D4: =C4 -> 10079558
A5: Extrudate | B5: =SUMIF(Artikelauswertung!$E$4:$E$12118,'Kategorien Summen'!A5,Artikelauswertung!$J$4:$J$12118) -> 1415461.1 | C5: =SUMIF(Artikelauswertung!$E$4:$E$12118,'Kategorien Summen'!A5,Artikelauswertung!$L$4:$L$12118) -> 1091260.8 | D5: bei Halbfabrikate
A6: Fertigwaren | B6: =SUMIF(Artikelauswertung!$E$4:$E$12118,'Kategorien Summen'!A6,Artikelauswertung!$J$4:$J$12118) -> 25271877 | C6: =SUMIF(Artikelauswertung!$E$4:$E$12118,'Kategorien Summen'!A6,Artikelauswertung!$L$4:$L$12118) -> 24934929 | D6: =C6*0.92 -> 22940135
A7: Halbfabrikate | B7: =SUMIF(Artikelauswertung!$E$4:$E$12118,'Kategorien Summen'!A7,Artikelauswertung!$J$4:$J$12118) -> 736720.51 | C7: =SUMIF(Artikelauswertung!$E$4:$E$12118,'Kategorien Summen'!A7,Artikelauswertung!$L$4:$L$12118) -> 545255.72 | D7: =C7+C5+C8 -> 3137857.7
A8: Monokroketten | B8: =SUMIF(Artikelauswertung!$E$4:$E$12118,'Kategorien Summen'!A8,Artikelauswertung!$J$4:$J$12118) -> 1946057.7 | C8: =SUMIF(Artikelauswertung!$E$4:$E$12118,'Kategorien Summen'!A8,Artikelauswertung!$L$4:$L$12118) -> 1501341.2 | D8: bei Halbfabrikate
A9: Rohstoffe | B9: =SUMIF(Artikelauswertung!$E$4:$E$12118,'Kategorien Summen'!A9,Artikelauswertung!$J$4:$J$12118) -> 14010401 | C9: =SUMIF(Artikelauswertung!$E$4:$E$12118,'Kategorien Summen'!A9,Artikelauswertung!$L$4:$L$12118) -> 15685651 | D9: =C9 -> 15685651
A10: Verpackungen | B10: =SUMIF(Artikelauswertung!$E$4:$E$12118,'Kategorien Summen'!A10,Artikelauswertung!$J$4:$J$12118) -> 3618866.7 | C10: =SUMIF(Artikelauswertung!$E$4:$E$12118,'Kategorien Summen'!A10,Artikelauswertung!$L$4:$L$12118) -> 16244287 | D10: =C10 -> 16244287
A11: Werbeartikel | B11: =SUMIF(Artikelauswertung!$E$4:$E$12118,'Kategorien Summen'!A11,Artikelauswertung!$J$4:$J$12118) -> 39733.893 | C11: =SUMIF(Artikelauswertung!$E$4:$E$12118,'Kategorien Summen'!A11,Artikelauswertung!$L$4:$L$12118) -> 539665.09 | D11: =C11 -> 539665.09
A12: Müll | B12: =SUMIF(Artikelauswertung!$E$4:$E$12118,'Kategorien Summen'!A12,Artikelauswertung!$J$4:$J$12118) -> 92670 | C12: =SUMIF(Artikelauswertung!$E$4:$E$12118,'Kategorien Summen'!A12,Artikelauswertung!$L$4:$L$12118) -> 11894.37 | D12: =C12 -> 11894.37 | F12: Kategorie gab es bisher nicht
A13: Gesamtergebnis | B13: =SUM(B4:B12) -> 49175624 | C13: =SUM(C4:C12) -> 70633842 | D13: =SUM(D4:D12) -> 68639048
A15: Anmerkung für 2024
A16: Bei der FW wurde Verpackungsschwund und Mischkosten, reduzierte Palettenpreise
A17: mit 8% in Abzug gebracht
A20: 2023 ist voraussichtlich nicht letzter Stand, wie gebucht. Die Zahlen müssten von Buchhaltung eingeholt werden und hier korrigiert werden.
B21: 2023
A22: Zeilenbeschriftungen | B22: Summe von Nettogewicht kg | C22: Summe von Bewertungspreis € | D22: Summen
A23: Ersatzteile | B23: 1047426.1 | C23: 271754.04 | D23: 271754.04 | F23: Zeile 2022 nicht vorhanden, 2021 vorhanden, aber mit 0 Euro
A24: Extrudate | B24: 1494408.2 | C24: 1231395.8 | D24: bei Halbfabrikate
A25: Fertigwaren | B25: 22347855 | C25: 21828709 | D25: 20082412
A26: Halbfabrikate | B26: 795656.88 | C26: 638660.71 | D26: 4085313.6
A27: Monokroketten | B27: 2448487.9 | C27: 2215257.1 | D27: bei Halbfabrikate
A28: Rohstoffe | B28: 9614552.6 | C28: 9583952.5 | D28: 9583952.5
A29: Verpackungen | B29: 3597567 | C29: 17512936 | D29: 17512936
A30: Werbeartikel | B30: 34182.173 | C30: 595012.96 | D30: 595012.96 | F30: Zeile 2022 nicht vorhanden, 2021 vorhanden, aber mit 0 Euro
A31: Gesamtergebnis | B31: 41380136 | C31: 53877678 | D31: 52131382
A33: Anmerkung für 2023
A34: Bei der FW wurde Verpackungsschwund und Mischkosten, reduzierte Palettenpreise | F34: Kann das wieder so angesetzt werden? Wir seit 2018 so angesetzt
A35: mit 8% in Abzug gebracht
A38: 2022
A39: Zeilenbeschriftungen | B39: Summe von Nettogewicht kg | C39: Summe von Bewertungspreis € | D39: Summen
A40: Extrudate | B40: 1433201.4 | C40: 891707.43 | D40: bei Halbfabrikate
A41: Fertigwaren | B41: 18064398 | C41: 19907182 | D41: =GETPIVOTDATA("Summe von Bewertungspreis €",$A$20,"Inventurgruppencode","Fertigwaren")*0.92 -> #REF!
A42: Halbfabrikate | B42: 439002.61 | C42: 277346.37 | D42: =GETPIVOTDATA("Summe von Bewertungspreis €",$A$20,"Inventurgruppencode","Halbfabrikate")+GETPIVOTDATA("Summe von Bewertungspreis €",$A$20,"Inventurgruppencode","Extrudate")+GETPIVOTDATA("Summe von Bewertungspreis €",$A$20,"Inventurgruppencode","Monokroketten") -> #REF!
A43: Monokroketten | B43: 1624891.2 | C43: 1176074.1 | D43: bei Halbfabrikate
A44: Rohstoffe | B44: 13146247 | C44: 11314141 | D44: =GETPIVOTDATA("Summe von Bewertungspreis €",$A$20,"Inventurgruppencode","Rohstoffe") -> #REF!
A45: Verpackungen | B45: 2740982.4 | C45: 15321361 | D45: =GETPIVOTDATA("Summe von Bewertungspreis €",$A$20,"Inventurgruppencode","Verpackungen") -> #REF!
A46: Gesamtergebnis | B46: 37448722 | C46: 48887811 | D46: =SUM(D40:D45) -> #REF!
A48: Anmerkung für 2022
A49: Bei der FW wurde Verpackungsschwund und Mischkosten, reduzierte Palettenpreise
A50: mit 8% in Abzug gebracht
A53: 2021 | E53: Vergleich zum VJ | G53: 2020 | K53: Vergleich zum VJ | M53: 2019 | O53: Vergleich zum VJ | Q53: 2018 | T53: 2017 | W53: 2016 | Z53: 2015
A54: Zeilenbeschriftungen | B54: Summe von Nettogewicht kg | C54: Summe von Bewertungspreis € | D54: Summen | G54: Zeilenbeschriftungen | H54: Summe von Nettogewicht | I54: Summe von Bewertungspreis | J54: Summen | M54: Ersatzteile/Motorenteile | N54: 0 | O54: 0 | Q54: Ersatzteile | R54: 0 | T54: Bezeichnung | U54: Summe von Bewertung | W54: Bezeichung | X54: Summe von Bewertung | Z54: Bezeichung | AA54: Summe von Bewertung
A55: Ersatzteile | B55: 9971 | C55: 0 | D55: 0 | G55: Ersatzteile | H55: 0 | I55: 0 | J55: 0 | M55: Fertigwaren | N55: 10706679 | O55: 0.0044 | Q55: Extrudate | R55: 823759.75 | T55: Fertigware | U55: 10195743 | W55: Roh- Hilfs- und Betriebsstoffe | X55: 12626612 | Z55: Roh- Hilfs- und Betriebsstoffe | AA55: 11472310
A56: Extrudate | B56: 1140508.2 | C56: 856739.16 | D56: bei Halbfabrikate | G56: Extrudate | H56: 810464.66 | I56: 672696.77 | J56: bei Halbfabrikate | M56: Halbfertigwaren | N56: 1677701.5 | O56: -0.024 | Q56: Fertigwaren | R56: 10660046 | T56: Unfertige Erzeugnisse | U56: 722932.57 | W56: unfertige Erzeugnisse | X56: 384635.18 | Z56: unfertige Erzeugnisse | AA56: 1085243
A57: Fertigwaren | B57: 21718789 | C57: 19669034 | D57: 18095511 | E57: 42.33 | G57: Fertigwaren | H57: 18626402 | I57: 13818892 | J57: =I57*0.92 -> 12713380 | K57: 18.74 | M57: Rohstoffe | N57: 4662107.8 | O57: -0.0074 | Q57: Halbfertigwaren | R57: 491496.5 | T57: Rohstoffe | U57: 4193418.5 | W57: fertige Erzeugnisse und Waren | X57: 9980752.6 | Z57: fertige Erzeugnisse und Waren | AA57: 7393942.2
A58: Halbfabrikate | B58: 268343.54 | C58: 130133.19 | D58: 1899060.8 | E58: 23.97 | G58: Halbfabrikate | H58: 429902.55 | I58: 290977.14 | J58: =I58+I59+I56 -> 1531899.2 | K58: -8.69 | M58: Verpackungen | N58: 8238119.3 | O58: -0.0062 | Q58: Monokroketten | R58: 403709.43 | T58: Verpackungen | U58: 8305827.7 | W58: Gesamt | X58: 22992000 | Z58: Gesamt | AA58: 19951495
A59: Monokroketten | B59: 1388053 | C59: 912188.47 | D59: bei Halbfabrikate | G59: Monokroketten | H59: 1006184.8 | I59: 568225.33 | J59: bei Halbfabrikate | M59: Werbeartikel | N59: 0 | O59: 0 | Q59: Motorenteile | R59: 0 | T59: Werkstatt | U59: 28667.55
A60: Rohstoffe | B60: 9796291.6 | C60: 8032887.8 | D60: 8032887.8 | E60: 32.89 | G60: Rohstoffe | H60: 6190242.4 | I60: 6044896.1 | J60: =I60 -> 6044896.1 | K60: 29.66 | M60: Gesamt | N60: 25284608 | O60: -0.0032 | Q60: Rohstoffe | R60: 4696738.7 | T60: Gas Heizöl Diesel AdBlue | U60: 15617.93
A61: Verpackungen | B61: 2500524.1 | C61: 11373810 | D61: 11373810 | E61: 14.28 | G61: Verpackungen | H61: 3058856.2 | I61: 9952404.6 | J61: =I61 -> 9952404.6 | K61: 20.81 | Q61: Verpackungen | R61: 8289649.2 | T61: Gesamt | U61: 23462207
A62: Werbeartikel | B62: 98491.951 | C62: 0 | D62: 0 | G62: Werbeartikel | H62: 122574.06 | I62: 0 | J62: 0 | K62: 0 | M62: Anmerkung für 2019 | Q62: Werbeartikel | R62: 0
A63: Gesamtergebnis | B63: 36920972 | C63: 40974792 | D63: =SUM(D55:D62) -> 39401269 | E63: 30.28 | G63: Gesamtergebnis | H63: =SUM(H55:H62) -> 30244627 | I63: =SUM(I55:I62) -> 31348092 | J63: =SUM(J55:J62) -> 30242580 | K63: 19.61 | M63: Bei der FW wurde Verpackungsschwund und Mischkosten, reduzierte Palettenpreise | Q63: Gesamt | R63: 25365400
M64: mit 8% in Abzug gebracht
A65: Anmerkung für 2021 | G65: Anmerkung für 2020 | Q65: Anmerkung für 2018:
A66: Bei der FW wurde Verpackungsschwund und Mischkosten, reduzierte Palettenpreise | G66: Bei der FW wurde Verpackungsschwund und Mischkosten, reduzierte Palettenpreise | Q66: Bei der FW wurde Verpackungsschwund und Mischkosten, reduzierte Palettenpreise mit 8% in Abzug gebracht.
A67: mit 8% in Abzug gebracht | G67: mit 8% in Abzug gebracht
