Workbook

Sheet Inventur_2023_Datensätze
A1: Auswertung zum 30.12.23
A2: Inventurauswertung per 30.12.2023
A4: Nr | B4: Beschreibung | C4: Beschreibung 2 | D4: Produktgruppencode | E4: Inventurgruppencode | F4: Bestand Datum | G4: Basiseinheit | H4: Nettogewicht kg/ Einheit | I4: Nettogewicht kg | J4: Bewertungspreis € / Einheit | K4: Bewertungspreis €
A5: 3000 | B5: Mehl 3000 Standard Geflügel | D5: 849 | E5: Halbfabrikate | F5: 1500 | G5: KG | H5: 1 | I5: =H5*F5 -> 1500 | J5: 0.3804 | K5: =F5*J5 -> 570.6
A6: 3024 | B6: T 3024 Mehl helle Farben | D6: 849 | E6: Halbfabrikate | F6: 0 | G6: KG | H6: 1 | I6: =H6*F6 -> 0 | J6: 0.3273 | K6: =F6*J6 -> 0
A7: 3042 | B7: VM Vorextrusion für 3056 | D7: 851 | E7: Extrudate | F7: 0 | G7: KG | H7: 1 | I7: =H7*F7 -> 0 | J7: 1.0197 | K7: =F7*J7 -> 0
A8: 3051 | B8: Vormischung Extrudiert für MM Gebackenes HF, Rind | D8: 849 | E8: Halbfabrikate | F8: 0 | G8: KG | H8: 1 | I8: =H8*F8 -> 0 | J8: 1.4696 | K8: =F8*J8 -> 0
A9: 3054 | B9: VM Dechra Treat Blend | C9: TEST | D9: 855 | E9: Extrudate | F9: 0 | G9: KG | H9: 1 | I9: =H9*F9 -> 0 | J9: 4.4492 | K9: =F9*J9 -> 0
A10: 3101 | B10: Vorextrusion für 3102 Mehl McAdams Award Snack | D10: 851 | E10: Extrudate | F10: 0 | G10: KG | H10: 1 | I10: =H10*F10 -> 0 | J10: 3.0395 | K10: =F10*J10 -> 0
A11: 3129 | B11: Mehl 3129 Geflügel | D11: 849 | E11: Halbfabrikate | F11: 10400 | G11: KG | H11: 1 | I11: =H11*F11 -> 10400 | J11: 0.3773 | K11: =F11*J11 -> 3923.92
A12: 3135 | B12: Mehl 3135 Geflügel Backlinie1 | D12: 849 | E12: Halbfabrikate | F12: 500 | G12: KG | H12: 1 | I12: =H12*F12 -> 500 | J12: 0.4666 | K12: =F12*J12 -> 233.3
A13: 5015 | B13: Premiere Adult Semi Moist | C13: braunes großes Stäbchen | D13: 853 | E13: Monokroketten | F13: 9400 | G13: KG | H13: 1 | I13: =H13*F13 -> 9400 | J13: 0.8176 | K13: =F13*J13 -> 7685.44
A14: 5017 | B14: Premiere Soft Junior Chicken | C14: braunes kleines Dreieck SOFT | D14: 853 | E14: Monokroketten | F14: 1400 | G14: KG | H14: 1 | I14: =H14*F14 -> 1400 | J14: 0.8957 | K14: =F14*J14 -> 1253.98
A15: 5026 | B15: BC Mini Frischfleisch | C15: brauner kleiner Zylinder | D15: 853 | E15: Monokroketten | F15: 1400 | G15: KG | H15: 1 | I15: =H15*F15 -> 1400 | J15: 1.1303 | K15: =F15*J15 -> 1582.42
A16: 5044 | B16: Buffo Single Ente No Grain | C16: braune mittelgroße Scheibe | D16: 853 | E16: Monokroketten | F16: 4500 | G16: KG | H16: 1 | I16: =H16*F16 -> 4500 | J16: 0.8159 | K16: =F16*J16 -> 3671.55
A17: 5045 | B17: Aldi High Premium NHMP | C17: braunes mittelgroßes Viereck | D17: 853 | E17: Monokroketten | F17: 4200 | G17: KG | H17: 1 | I17: =H17*F17 -> 4200 | J17: 0.5871 | K17: =F17*J17 -> 2465.82
A18: 5053 | B18: Katze HP Senior m. Frischfleisch | C18: hellbraune kleine Scheibe | D18: 853 | E18: Monokroketten | F18: 30892.012 | G18: KG | H18: 1 | I18: =H18*F18 -> 30892.012 | J18: 0.9382 | K18: =F18*J18 -> 28982.886
A19: 5054 | B19: Sanabelle Hairball-Snack Relaunch | C19: braune kleine Scheibe | D19: 853 | E19: Monokroketten | F19: 750 | G19: KG | H19: 1 | I19: =H19*F19 -> 750 | J19: 1.3891 | K19: =F19*J19 -> 1041.825
A20: 5056 | B20: Sanabelle Thanks-Snack Relaunch | C20: braunes mittelgroßes Herz | D20: 853 | E20: Monokroketten | F20: 10764.94 | G20: KG | H20: 1 | I20: =H20*F20 -> 10764.94 | J20: 1.3278 | K20: =F20*J20 -> 14293.687
A21: 5059 | B21: HPC soft Plus Ziege | C21: braunes großes Viereck SOFT | D21: 853 | E21: Monokroketten | F21: 32600 | G21: KG | H21: 1 | I21: =H21*F21 -> 32600 | J21: 1.3063 | K21: =F21*J21 -> 42585.38
A22: 5062 | B22: Briantos Adult Lachs & Reis | C22: braune große Scheibe | D22: 853 | E22: Monokroketten | F22: 0 | G22: KG | H22: 1 | I22: =H22*F22 -> 0 | J22: 0.6405 | K22: =F22*J22 -> 0
A23: 5067 | B23: Briantos Adult Maxi Huhn & Reis | C23: braune große Scheibe | D23: 853 | E23: Monokroketten | F23: 9139.721 | G23: KG | H23: 1 | I23: =H23*F23 -> 9139.721 | J23: 0.6422 | K23: =F23*J23 -> 5869.5288
A24: 5070 | B24: HPC Soft Hühnchen & Banane | C24: braunes großes Viereck SOFT | D24: 853 | E24: Monokroketten | F24: 0 | G24: KG | H24: 1 | I24: =H24*F24 -> 0 | J24: 0.7801 | K24: =F24*J24 -> 0
... A164: 6185 | B164: Pets at Home Dental Stick | C164: softer Dental Stick | D164: 848 | E164: Halbfabrikate | F164: 0 | G164: KG | H164: 1 | I164: =H164*F164 -> 0 | J164: 0.6918 | K164: =F164*J164 -> 0
A165: 6204 | B165: Cat Sticks Lachs & Forelle | D165: 848 | E165: Halbfabrikate | F165: 0 | G165: KG | H165: 1 | I165: =H165*F165 -> 0 | J165: 1.5515 | K165: =F165*J165 -> 0
A166: 6205 | B166: Dog Sticks Geflügel | C166: bräunlicher DogStick | D166: 848 | E166: Halbfabrikate | F166: 0 | G166: KG | H166: 1 | I166: =H166*F166 -> 0 | J166: 1.5862 | K166: =F166*J166 -> 0
A167: 6206 | B167: Dog Sticks Rind | C167: rötlicher Dog Stick | D167: 848 | E167: Halbfabrikate | F167: 0 | G167: KG | H167: 1 | I167: =H167*F167 -> 0 | J167: 2.135 | K167: =F167*J167 -> 0
A168: 6209 | B168: Dog Sticks Mercadona Chicken Liver | C168: Dog Stick | D168: 848 | E168: Halbfabrikate | F168: 0 | G168: KG | H168: 1 | I168: =H168*F168 -> 0 | J168: 1.7358 | K168: =F168*J168 -> 0
A169: 6210 | B169: Mercadona Dog Sticks Lachs mit Rote Beete | C169: Dog Stick | D169: 848 | E169: Halbfabrikate | F169: 0 | G169: KG | H169: 1 | I169: =H169*F169 -> 0 | J169: 1.5445 | K169: =F169*J169 -> 0
A170: 6211 | B170: Aldi Cat Sticks Lamm, Truthahn, Yucca, Taurin | D170: 848 | E170: Halbfabrikate | F170: 0 | G170: KG | H170: 1 | I170: =H170*F170 -> 0 | J170: 2.9061 | K170: =F170*J170 -> 0
A171: 6212 | B171: Aldi Cat Sticks Geflügel, Leber, Yucca, Taurin | D171: 848 | E171: Halbfabrikate | F171: 0 | G171: KG | H171: 1 | I171: =H171*F171 -> 0 | J171: 1.5601 | K171: =F171*J171 -> 0
A172: 6213 | B172: Aldi Cat Sticks Lachs, Forelle, Yucca, Taurin | D172: 848 | E172: Halbfabrikate | F172: 0 | G172: KG | H172: 1 | I172: =H172*F172 -> 0 | J172: 2.1176 | K172: =F172*J172 -> 0
A173: 6217 | B173: Sanabelle Snack Seelachs & Feige MSC | D173: 848 | E173: Halbfabrikate | F173: 0 | G173: KG | H173: 1 | I173: =H173*F173 -> 0 | J173: 1.9205 | K173: =F173*J173 -> 0
A174: 6225 | B174: fit+fun Sticks Kaninchen & Pute & Hefe | D174: 848 | E174: Halbfabrikate | F174: 0 | G174: KG | H174: 1 | I174: =H174*F174 -> 0 | J174: 1.6644 | K174: =F174*J174 -> 0
A175: 6242 | B175: Cat Stick kurz! Lamm, Katzenminze | D175: 848 | E175: Halbfabrikate | F175: 0 | G175: KG | H175: 1 | I175: =H175*F175 -> 0 | J175: 1.9055 | K175: =F175*J175 -> 0
A176: 6249 | B176: Dog Sticks Gen. II | C176: Brauner Dog Stick 12/13 mm | D176: 848 | E176: Halbfabrikate | F176: 0 | G176: KG | H176: 1 | I176: =H176*F176 -> 0 | J176: 1.7963 | K176: =F176*J176 -> 0
A177: 6255 | B177: Cat Sticks Quattrofahne Apfel | D177: 848 | E177: Halbfabrikate | F177: 0 | G177: KG | H177: 1 | I177: =H177*F177 -> 0 | J177: 1.4914 | K177: =F177*J177 -> 0
A178: 6256 | B178: Cat Sticks Quattrofahne Karotte | D178: 848 | E178: Halbfabrikate | F178: 0 | G178: KG | H178: 1 | I178: =H178*F178 -> 0 | J178: 1.6728 | K178: =F178*J178 -> 0
A179: 6257 | B179: Cat Sticks Quattrofahne Tomate | D179: 848 | E179: Halbfabrikate | F179: 0 | G179: KG | H179: 1 | I179: =H179*F179 -> 0 | J179: 2.28 | K179: =F179*J179 -> 0
A180: 6258 | B180: Cat Sticks Quattrofahnen Petersilie | C180: rotbraun normale Sticks | D180: 848 | E180: Halbfabrikate | F180: 0 | G180: KG | H180: 1 | I180: =H180*F180 -> 0 | J180: 2.2509 | K180: =F180*J180 -> 0
A181: 6260 | B181: Dog Sticks mit Leberwurst | C181: rötlich-Brauner Dog Stick 13 mm | D181: 848 | E181: Halbfabrikate | F181: 0 | G181: KG | H181: 1 | I181: =H181*F181 -> 0 | J181: 1.5582 | K181: =F181*J181 -> 0
A182: 6261 | B182: Dog Sticks mit Käse | C182: Dog Stick | D182: 848 | E182: Halbfabrikate | F182: 0 | G182: KG | H182: 1 | I182: =H182*F182 -> 0 | J182: 1.7495 | K182: =F182*J182 -> 0
A183: 6267 | B183: Rocketo Bio Organic Skin & Coat Treat | C183: Dogsticks kurz abgeschnitten | D183: 848 | E183: Halbfabrikate | F183: 0 | G183: KG | H183: 1 | I183: =H183*F183 -> 0 | J183: 0.0672 | K183: =F183*J183 -> 0
A184: 6281 | B184: Mercadona Compy Cat Sticks Lachs & Forelle | C184: Brauner Stick | D184: 848 | E184: Halbfabrikate | F184: 0 | G184: KG | H184: 1 | I184: =H184*F184 -> 0 | J184: 1.8413 | K184: =F184*J184 -> 0
A185: 6284 | B185: Cat Stick Huhn Ente Gen. II | C185: softer Catstick | D185: 848 | E185: Halbfabrikate | F185: 0 | G185: KG | H185: 1 | I185: =H185*F185 -> 0 | J185: 1.5716 | K185: =F185*J185 -> 0
A186: 6285 | B186: Cat Stick Geflügel Leber Katzengras Gen. II | C186: softer Catstick | D186: 848 | E186: Halbfabrikate | F186: 0 | G186: KG | H186: 1 | I186: =H186*F186 -> 0 | J186: 2.1353 | K186: =F186*J186 -> 0
A187: 6286 | B187: Cat Sticks Kalb & Lamm | C187: softer Catstick | D187: 848 | E187: Halbfabrikate | F187: 0 | G187: KG | H187: 1 | I187: =H187*F187 -> 0 | J187: 1.8668 | K187: =F187*J187 -> 0
A188: 6289 | B188: Dog Sticks Rind Rote Beete Gen. II | C188: Dog Stick | D188: 848 | E188: Halbfabrikate | F188: 0 | G188: KG | H188: 1 | I188: =H188*F188 -> 0 | J188: 2.7936 | K188: =F188*J188 -> 0
A189: 6301 | B189: Saftige Würstchen Rind | C189: rötliches Würstchen in Haut | D189: 848 | E189: Halbfabrikate | F189: 0 | G189: KG | H189: 1 | I189: =H189*F189 -> 0 | J189: 2.9335 | K189: =F189*J189 -> 0
A190: 6454 | B190: Dog Stick Mono Protein Huhn | C190: Dog Sticks kurz | D190: 848 | E190: Halbfabrikate | F190: 0 | G190: KG | H190: 1 | I190: =H190*F190 -> 0 | J190: 4.7866 | K190: =F190*J190 -> 0
A191: 6486 | B191: DOG E PUP BITE DUCK | C191: Shortstick 12 mm | D191: 848 | E191: Halbfabrikate | F191: 0 | G191: KG | H191: 1 | I191: =H191*F191 -> 0 | J191: 1.087 | K191: =F191*J191 -> 0
... A222: 6993 | B222: Ex.Cat roter Mond 4 % Garnele 4% Forelle | C222: roter mittelgroßer Mond | D222: 851 | E222: Extrudate | F222: 4763 | G222: KG | H222: 1 | I222: =H222*F222 -> 4763 | J222: 0.5583 | K222: =F222*J222 -> 2659.1829
A223: 7000 | B223: VM Superfood-Mix Arden Grange | D223: 855 | E223: Extrudate | F223: 154 | G223: KG | H223: 1 | I223: =H223*F223 -> 154 | J223: 3.7917 | K223: =F223*J223 -> 583.9218
A224: 7804 | B224: Zwischenm. Soft Brocken Mix | D224: 852 | E224: Halbfabrikate | F224: 3500 | G224: KG | H224: 1 | I224: =H224*F224 -> 3500 | J224: 0.3631 | K224: =F224*J224 -> 1270.85
A225: 7818 | B225: Zwischenm. Ex. Adult Menue | D225: 852 | E225: Halbfabrikate | F225: 16100 | G225: KG | H225: 1 | I225: =H225*F225 -> 16100 | J225: 0.4451 | K225: =F225*J225 -> 7166.11
A226: 7819 | B226: Zwischenm. Multifit Senior neu | D226: 852 | E226: Halbfabrikate | F226: 6500 | G226: KG | H226: 1 | I226: =H226*F226 -> 6500 | J226: 0.4881 | K226: =F226*J226 -> 3172.65
A227: 7820 | B227: Zwischenmischung MF Adult | D227: 852 | E227: Halbfabrikate | F227: 10500 | G227: KG | H227: 1 | I227: =H227*F227 -> 10500 | J227: 0.3619 | K227: =F227*J227 -> 3799.95
A228: 7824 | B228: Ex. Kaufland Rind & Gemüse | C228: braunes großes Stäbchen | D228: 851 | E228: Extrudate | F228: 81168.499 | G228: KG | H228: 1 | I228: =H228*F228 -> 81168.499 | J228: 0.2634 | K228: =F228*J228 -> 21379.783
A229: 7833 | B229: Ex.Dog brauner Knochen 4 % Geflügel | C229: Brauner großer Knochen | D229: 851 | E229: Extrudate | F229: 6684 | G229: KG | H229: 1 | I229: =H229*F229 -> 6684 | J229: 0.3655 | K229: =F229*J229 -> 2443.002
A230: 7907 | B230: Lidl Gourmet Adult kleine Rassen | C230: Braune kleine Scheibe | D230: 853 | E230: Monokroketten | F230: 450 | G230: KG | H230: 1 | I230: =H230*F230 -> 450 | J230: 0.3817 | K230: =F230*J230 -> 171.765
A231: 7911 | B231: Mehlmischung E & C Dentasticks Apple | D231: 851 | E231: Extrudate | F231: 10219.33 | G231: KG | H231: 1 | I231: =H231*F231 -> 10219.33 | J231: 0.9537 | K231: =F231*J231 -> 9746.175
A232: 7913 | B232: VM Vorextrusion für 8130 Lily | D232: 851 | E232: Extrudate | F232: 770 | G232: KG | H232: 1 | I232: =H232*F232 -> 770 | J232: 0.906 | K232: =F232*J232 -> 697.62
A233: 7914 | B233: VM Vorextrusion für 8134 Lily Kitchen Cat Chicken | D233: 851 | E233: Extrudate | F233: 0 | G233: KG | H233: 1 | I233: =H233*F233 -> 0 | J233: 0.676 | K233: =F233*J233 -> 0
A234: 7916 | B234: VM Vorextrusion für 6802 | D234: 851 | E234: Extrudate | F234: 51 | G234: KG | H234: 1 | I234: =H234*F234 -> 51 | J234: 1.7007 | K234: =F234*J234 -> 86.7357
A235: 7928 | B235: Ex. für Adult Menü Relaunch | C235: Braune große Fledermaus | D235: 851 | E235: Extrudate | F235: 27646.85 | G235: KG | H235: 1 | I235: =H235*F235 -> 27646.85 | J235: 0.6468 | K235: =F235*J235 -> 17881.983
A236: 7949 | B236: Ex.Dog braunes Viereck 4% Rind 4 % Geflügel | C236: braunes großes Viereck | D236: 851 | E236: Extrudate | F236: 40407.8 | G236: KG | H236: 1 | I236: =H236*F236 -> 40407.8 | J236: 0.2767 | K236: =F236*J236 -> 11180.838
A237: 7953 | B237: VM Vorextrusion für 3462 mit 9135 + 9368 | D237: 851 | E237: Extrudate | F237: 0 | G237: KG | H237: 1 | I237: =H237*F237 -> 0 | J237: 1.0683 | K237: =F237*J237 -> 0
A238: 7954 | B238: Ex. gelbe Scheibe | C238: gelbe große Scheibe | D238: 851 | E238: Extrudate | F238: 7050 | G238: KG | H238: 1 | I238: =H238*F238 -> 7050 | J238: 0.3393 | K238: =F238*J238 -> 2392.065
A239: 7957 | B239: VM Vorextrusion für 3066 & 3466 | D239: 851 | E239: Extrudate | F239: 0 | G239: KG | H239: 1 | I239: =H239*F239 -> 0 | J239: 1.0054 | K239: =F239*J239 -> 0
A240: 7971 | B240: Gourmet Hundetrockenfutter Adult Mini | C240: Braune kleine Scheibe | D240: 853 | E240: Monokroketten | F240: 11559.43 | G240: KG | H240: 1 | I240: =H240*F240 -> 11559.43 | J240: 0.4361 | K240: =F240*J240 -> 5041.0674
A241: 7973 | B241: Gourmet Hundetrockenfutter Balance Mini | C241: Braunes kleines Viereck | D241: 853 | E241: Monokroketten | F241: 19631.93 | G241: KG | H241: 1 | I241: =H241*F241 -> 19631.93 | J241: 0.3476 | K241: =F241*J241 -> 6824.0589
A242: 7977 | B242: Ex.Dog brauner Knochen 4 % Reis 4 % Hirse | C242: hellbrauner großer Knochen | D242: 851 | E242: Extrudate | F242: 20679.6 | G242: KG | H242: 1 | I242: =H242*F242 -> 20679.6 | J242: 0.242 | K242: =F242*J242 -> 5004.4632
A243: 7979 | B243: Ex.Dog rotes geriffeltes Ei 4 % Rind 4 % Erbsen | C243: rotes großes geriffeltes Ei | D243: 851 | E243: Extrudate | F243: 85439.7 | G243: KG | H243: 1 | I243: =H243*F243 -> 85439.7 | J243: 0.2547 | K243: =F243*J243 -> 21761.492
A244: 7981 | B244: Ex. Karotte Hund lang | C244: Oranges großes Dreieck | D244: 851 | E244: Extrudate | F244: 8120 | G244: KG | H244: 1 | I244: =H244*F244 -> 8120 | J244: 0.3697 | K244: =F244*J244 -> 3001.964
A245: 7989 | B245: Ex. grüne dicke runde Scheibe | C245: Grüne mittelgroße Scheibe | D245: 851 | E245: Extrudate | F245: 16425.75 | G245: KG | H245: 1 | I245: =H245*F245 -> 16425.75 | J245: 0.3009 | K245: =F245*J245 -> 4942.5082
A246: 8004 | B246: Wolfsblut Adult Wide Plain Horse | C246: Braunes mittelgroßes Dreieck | D246: 853 | E246: Monokroketten | F246: 16771.1 | G246: KG | H246: 1 | I246: =H246*F246 -> 16771.1 | J246: 0.5362 | K246: =F246*J246 -> 8992.6638
A247: 8028 | B247: Zooplus Rocco Hund Adult Fisch | C247: braunes mittelgroßes Viereck | D247: 853 | E247: Monokroketten | F247: 700 | G247: KG | H247: 1 | I247: =H247*F247 -> 700 | J247: 1.6411 | K247: =F247*J247 -> 1148.77
A248: 8035 | B248: Wolf of Wilderness Junior Huhn Wide Acres Soft | C248: Braunes mittelgroßes Viereck Soft | D248: 853 | E248: Monokroketten | F248: 0 | G248: KG | H248: 1 | I248: =H248*F248 -> 0 | J248: 1.0785 | K248: =F248*J248 -> 0
A249: 8036 | B249: Wolf of Wilderness Senior Huhn Wide Acres, Soft | C249: Braunes mittelgroßes Viereck Soft | D249: 853 | E249: Monokroketten | F249: 0 | G249: KG | H249: 1 | I249: =H249*F249 -> 0 | J249: 1.3509 | K249: =F249*J249 -> 0
A250: 8037 | B250: Wolf of Wilderness Adult Lachs Blue River, Soft | C250: Braunes mittelgroßes Viereck Soft | D250: 853 | E250: Monokroketten | F250: 0 | G250: KG | H250: 1 | I250: =H250*F250 -> 0 | J250: 1.2071 | K250: =F250*J250 -> 0
A251: 8039 | B251: Wolfsblut Wild Duck Puppy Small Breed | C251: Dunkelbraunes kleines Viereck | D251: 853 | E251: Monokroketten | F251: 16685.75 | G251: KG | H251: 1 | I251: =H251*F251 -> 16685.75 | J251: 1.1562 | K251: =F251*J251 -> 19292.064
... A306: 8426 | B306: TEST Lilys Kitchen Dog Wild Woodland Walk | C306: Braune mittelgroße Scheibe | D306: 853 | E306: Monokroketten | F306: 4200 | G306: KG | H306: 1 | I306: =H306*F306 -> 4200 | J306: 1.5771 | K306: =F306*J306 -> 6623.82
A307: 9010 | B307: VM für 6200 Gourmetstreifen SNACK | D307: 855 | E307: Extrudate | F307: 400 | G307: KG | H307: 1 | I307: =H307*F307 -> 400 | J307: 1.4794 | K307: =F307*J307 -> 591.76
A308: 9013 | B308: VM Filets Gen IV SNACK | D308: 855 | E308: Extrudate | F308: 0 | G308: KG | H308: 1 | I308: =H308*F308 -> 0 | J308: 3.5089 | K308: =F308*J308 -> 0
A309: 9022 | B309: VM 6266 Rocketo Organic Gut Treat SNACK | D309: 855 | E309: Extrudate | F309: 300 | G309: KG | H309: 1 | I309: =H309*F309 -> 300 | J309: 0.0905 | K309: =F309*J309 -> 27.15
A310: 9023 | B310: VM für 6265 Rocketo Organic Dental Treat SNACK | D310: 855 | E310: Extrudate | F310: 60 | G310: KG | H310: 1 | I310: =H310*F310 -> 60 | J310: 0.1128 | K310: =F310*J310 -> 6.768
A311: 9026 | B311: BC Lamb & Rice AB - Relaunch 2017 | C311: Braunes mittelgroßes Dreieck | D311: 853 | E311: Monokroketten | F311: 700 | G311: KG | H311: 1 | I311: =H311*F311 -> 700 | J311: 1.0359 | K311: =F311*J311 -> 725.13
A312: 9030 | B312: VM für 5462 Superfood Canagan | D312: 855 | E312: Extrudate | F312: 1081.659 | G312: KG | H312: 1 | I312: =H312*F312 -> 1081.659 | J312: 2.6905 | K312: =F312*J312 -> 2910.2035
A313: 9035 | B313: VM Früchte/Gemüse für Symply Canagan | D313: 855 | E313: Extrudate | F313: 159.996 | G313: KG | H313: 1 | I313: =H313*F313 -> 159.996 | J313: 3.4967 | K313: =F313*J313 -> 559.45801
A314: 9038 | B314: 9038 VM Geflügelmehle für 6510 SNACK | D314: 855 | E314: Extrudate | F314: 850 | G314: KG | H314: 1 | I314: =H314*F314 -> 850 | J314: 0.872 | K314: =F314*J314 -> 741.2
A315: 9039 | B315: 9039 VM Catsticks für 6510 | D315: 855 | E315: Extrudate | F315: 500 | G315: KG | H315: 1 | I315: =H315*F315 -> 500 | J315: 2.0738 | K315: =F315*J315 -> 1036.9
A316: 9047 | B316: 6031 Füllung Gelenk Fit | C316: ohne TiOx | D316: 848 | E316: Halbfabrikate | F316: 0 | G316: KG | H316: 1 | I316: =H316*F316 -> 0 | J316: 1.0451 | K316: =F316*J316 -> 0
A317: 9053 | B317: Mehl Kern 6024 | D317: 848 | E317: Halbfabrikate | F317: 2213.4965 | G317: KG | H317: 1 | I317: =H317*F317 -> 2213.4965 | J317: 0.483 | K317: =F317*J317 -> 1069.1188
A318: 9054 | B318: Mehl Mantel 6024 | D318: 848 | E318: Halbfabrikate | F318: 4726.7788 | G318: KG | H318: 1 | I318: =H318*F318 -> 4726.7788 | J318: 0.5143 | K318: =F318*J318 -> 2430.9824
A319: 9058 | B319: Mehlmischung Mantel für 6095 Megakaubarren CIAM GF | D319: 851 | E319: Extrudate | F319: 221 | G319: KG | H319: 1 | I319: =H319*F319 -> 221 | J319: 1.1597 | K319: =F319*J319 -> 256.2937
A320: 9059 | B320: VM Gelatine Tanninsäure | D320: 855 | E320: Extrudate | F320: 0 | G320: KG | H320: 1 | I320: =H320*F320 -> 0 | J320: 7.2518 | K320: =F320*J320 -> 0
A321: 9062 | B321: LK on the go bars – chicken Mehlmischung SNACK | D321: 855 | E321: Extrudate | F321: 1800 | G321: KG | H321: 1 | I321: =H321*F321 -> 1800 | J321: 2.5152 | K321: =F321*J321 -> 4527.36
A322: 9068 | B322: Mehl für 6293 E&C Früchte Bars SNACK | C322: KK 9024 | D322: 855 | E322: Extrudate | F322: 360 | G322: KG | H322: 1 | I322: =H322*F322 -> 360 | J322: 0.9796 | K322: =F322*J322 -> 352.656
A323: 9107 | B323: VM Pferdefett | D323: 857 | E323: Extrudate | F323: 872.71 | G323: KG | H323: 1 | I323: =H323*F323 -> 872.71 | J323: 0.0541 | K323: =F323*J323 -> 47.213611
A324: 9201 | B324: VM R200 + R557 FF Tank | D324: 856 | E324: Extrudate | F324: 0 | G324: KG | H324: 1 | I324: =H324*F324 -> 0 | J324: 0.6004 | K324: =F324*J324 -> 0
...

Sheet Inventur_2023_Kategorien
B2: 2023
A3: Zeilenbeschriftungen | B3: Summe von Nettogewicht kg | C3: Summe von Bewertungspreis € | D3: Summen
A4: Ersatzteile | B4: =SUMIF(Inventur_2023_Datensätze!$E$5:$E$10959,A4, Inventur_2023_Datensätze!$I$5:$I$10959) -> 107375.32 | C4: =SUMIF(Inventur_2023_Datensätze!$E$5:$E$10959, A4,Inventur_2023_Datensätze!$K$5:$K$10959) -> 389676.22 | D4: =C4 -> 389676.22 | F4: War früher extra Liste. Jetzt eine komplette Datei | I4: davon rein Ersatzteile | J4: 284694.58
A5: Extrudate | B5: =SUMIF(Inventur_2023_Datensätze!$E$5:$E$10959,A5, Inventur_2023_Datensätze!$I$5:$I$10959) -> 1494408.2 | C5: =SUMIF(Inventur_2023_Datensätze!$E$5:$E$10959, A5,Inventur_2023_Datensätze!$K$5:$K$10959) -> 1231395.8 | D5: bei Halbfabrikate | I5: davon nur Diesel | J5: 82704.28
A6: Fertigwaren | B6: =SUMIF(Inventur_2023_Datensätze!$E$5:$E$10959,A6, Inventur_2023_Datensätze!$I$5:$I$10959) -> 22344255 | C6: =SUMIF(Inventur_2023_Datensätze!$E$5:$E$10959, A6,Inventur_2023_Datensätze!$K$5:$K$10959) -> 21821297 | D6: =C6*0.92 -> 20075594 | I6: davon nur Heizöl | J6: 13032.6
A7: Halbfabrikate | B7: =SUMIF(Inventur_2023_Datensätze!$E$5:$E$10959,A7, Inventur_2023_Datensätze!$I$5:$I$10959) -> 795656.88 | C7: =SUMIF(Inventur_2023_Datensätze!$E$5:$E$10959, A7,Inventur_2023_Datensätze!$K$5:$K$10959) -> 638660.71 | D7: =C7+C5+C8 -> 3938188.7 | I7: davon nur Gas Propan | J7: 6195.7
A8: Monokroketten | B8: =SUMIF(Inventur_2023_Datensätze!$E$5:$E$10959,A8, Inventur_2023_Datensätze!$I$5:$I$10959) -> 2213486.9 | C8: =SUMIF(Inventur_2023_Datensätze!$E$5:$E$10959, A8,Inventur_2023_Datensätze!$K$5:$K$10959) -> 2068132.1 | D8: bei Halbfabrikate | I8: davon nur Gas Stapler | J8: 3049.06
A9: Rohstoffe | B9: =SUMIF(Inventur_2023_Datensätze!$E$5:$E$10959,A9, Inventur_2023_Datensätze!$I$5:$I$10959) -> 10087519 | C9: =SUMIF(Inventur_2023_Datensätze!$E$5:$E$10959, A9,Inventur_2023_Datensätze!$K$5:$K$10959) -> 9901043.8 | D9: =C9 -> 9901043.8 | I9: Summe: | J9: =SUM(J4:J8) -> 389676.22
A10: Verpackungen | B10: =SUMIF(Inventur_2023_Datensätze!$E$5:$E$10959,A10, Inventur_2023_Datensätze!$I$5:$I$10959) -> 3597567 | C10: =SUMIF(Inventur_2023_Datensätze!$E$5:$E$10959, A10,Inventur_2023_Datensätze!$K$5:$K$10959) -> 17512936 | D10: =C10 -> 17512936
A11: Werbeartikel | B11: =SUMIF(Inventur_2023_Datensätze!$E$5:$E$10959,A11, Inventur_2023_Datensätze!$I$5:$I$10959) -> 23766.36 | C11: =SUMIF(Inventur_2023_Datensätze!$E$5:$E$10959, A11,Inventur_2023_Datensätze!$K$5:$K$10959) -> 0 | D11: =C11 -> 0
A12: Gesamtergebnis | B12: =SUM(B4:B11) -> 40664035 | C12: =SUM(C4:C11) -> 53563142 | D12: =SUM(D4:D11) -> 51817438
A14: Anmerkung für 2023
A15: Bei der FW wurde Verpackungsschwund und Mischkosten, reduzierte Palettenpreise | F15: Kann das wieder so angesetzt werden? Wird seit 2018 so angesetzt .
A16: mit 8% in Abzug gebracht
A19: 2022
A20: Zeilenbeschriftungen | B20: Summe von Nettogewicht kg | C20: Summe von Bewertungspreis € | D20: Summen
A21: Extrudate | B21: 1433201.4 | C21: 891707.43 | D21: bei Halbfabrikate
A22: Fertigwaren | B22: 18064398 | C22: 19907182 | D22: =GETPIVOTDATA("Summe von Bewertungspreis €",$A$20,"Inventurgruppencode","Fertigwaren")*0.92 -> 18314607
A23: Halbfabrikate | B23: 439002.61 | C23: 277346.37 | D23: =GETPIVOTDATA("Summe von Bewertungspreis €",$A$20,"Inventurgruppencode","Halbfabrikate")+GETPIVOTDATA("Summe von Bewertungspreis €",$A$20,"Inventurgruppencode","Extrudate")+GETPIVOTDATA("Summe von Bewertungspreis €",$A$20,"Inventurgruppencode","Monokroketten") -> 2345127.9
A24: Monokroketten | B24: 1624891.2 | C24: 1176074.1 | D24: bei Halbfabrikate
A25: Rohstoffe | B25: 13146247 | C25: 11314141 | D25: =GETPIVOTDATA("Summe von Bewertungspreis €",$A$20,"Inventurgruppencode","Rohstoffe") -> 11314141
A26: Verpackungen | B26: 2740982.4 | C26: 15321361 | D26: =GETPIVOTDATA("Summe von Bewertungspreis €",$A$20,"Inventurgruppencode","Verpackungen") -> 15321361
A27: Gesamtergebnis | B27: 37448722 | C27: 48887811 | D27: =SUM(D21:D26) -> 47295237
A29: Anmerkung für 2022
A30: Bei der FW wurde Verpackungsschwund und Mischkosten, reduzierte Palettenpreise
A31: mit 8% in Abzug gebracht
A34: 2021 | E34: Vergleich zum VJ | G34: 2020 | K34: Vergleich zum VJ | M34: 2019 | O34: Vergleich zum VJ | Q34: 2018 | T34: 2017 | W34: 2016 | Z34: 2015
A35: Zeilenbeschriftungen | B35: Summe von Nettogewicht kg | C35: Summe von Bewertungspreis € | D35: Summen | G35: Zeilenbeschriftungen | H35: Summe von Nettogewicht | I35: Summe von Bewertungspreis | J35: Summen | M35: Ersatzteile/Motorenteile | N35: 0 | O35: 0 | Q35: Ersatzteile | R35: 0 | T35: Bezeichnung | U35: Summe von Bewertung | W35: Bezeichung | X35: Summe von Bewertung | Z35: Bezeichung | AA35: Summe von Bewertung
A36: Ersatzteile | B36: 9971 | C36: 0 | D36: 0 | G36: Ersatzteile | H36: 0 | I36: 0 | J36: 0 | M36: Fertigwaren | N36: 10706679 | O36: 0.0044 | Q36: Extrudate | R36: 823759.75 | T36: Fertigware | U36: 10195743 | W36: Roh- Hilfs- und Betriebsstoffe | X36: 12626612 | Z36: Roh- Hilfs- und Betriebsstoffe | AA36: 11472310
A37: Extrudate | B37: 1140508.2 | C37: 856739.16 | D37: bei Halbfabrikate | G37: Extrudate | H37: 810464.66 | I37: 672696.77 | J37: bei Halbfabrikate | M37: Halbfertigwaren | N37: 1677701.5 | O37: -0.024 | Q37: Fertigwaren | R37: 10660046 | T37: Unfertige Erzeugnisse | U37: 722932.57 | W37: unfertige Erzeugnisse | X37: 384635.18 | Z37: unfertige Erzeugnisse | AA37: 1085243
A38: Fertigwaren | B38: 21718789 | C38: 19669034 | D38: 18095511 | E38: 42.33 | G38: Fertigwaren | H38: 18626402 | I38: 13818892 | J38: =I38*0.92 -> 12713380 | K38: 18.74 | M38: Rohstoffe | N38: 4662107.8 | O38: -0.0074 | Q38: Halbfertigwaren | R38: 491496.5 | T38: Rohstoffe | U38: 4193418.5 | W38: fertige Erzeugnisse und Waren | X38: 9980752.6 | Z38: fertige Erzeugnisse und Waren | AA38: 7393942.2
A39: Halbfabrikate | B39: 268343.54 | C39: 130133.19 | D39: 1899060.8 | E39: 23.97 | G39: Halbfabrikate | H39: 429902.55 | I39: 290977.14 | J39: =I39+I40+I37 -> 1531899.2 | K39: -8.69 | M39: Verpackungen | N39: 8238119.3 | O39: -0.0062 | Q39: Monokroketten | R39: 403709.43 | T39: Verpackungen | U39: 8305827.7 | W39: Gesamt | X39: 22992000 | Z39: Gesamt | AA39: 19951495
A40: Monokroketten | B40: 1388053 | C40: 912188.47 | D40: bei Halbfabrikate | G40: Monokroketten | H40: 1006184.8 | I40: 568225.33 | J40: bei Halbfabrikate | M40: Werbeartikel | N40: 0 | O40: 0 | Q40: Motorenteile | R40: 0 | T40: Werkstatt | U40: 28667.55
A41: Rohstoffe | B41: 9796291.6 | C41: 8032887.8 | D41: 8032887.8 | E41: 32.89 | G41: Rohstoffe | H41: 6190242.4 | I41: 6044896.1 | J41: =I41 -> 6044896.1 | K41: 29.66 | M41: Gesamt | N41: 25284608 | O41: -0.0032 | Q41: Rohstoffe | R41: 4696738.7 | T41: Gas Heizöl Diesel AdBlue | U41: 15617.93
A42: Verpackungen | B42: 2500524.1 | C42: 11373810 | D42: 11373810 | E42: 14.28 | G42: Verpackungen | H42: 3058856.2 | I42: 9952404.6 | J42: =I42 -> 9952404.6 | K42: 20.81 | Q42: Verpackungen | R42: 8289649.2 | T42: Gesamt | U42: 23462207
A43: Werbeartikel | B43: 98491.951 | C43: 0 | D43: 0 | G43: Werbeartikel | H43: 122574.06 | I43: 0 | J43: 0 | K43: 0 | M43: Anmerkung für 2019 | Q43: Werbeartikel | R43: 0
A44: Gesamtergebnis | B44: 36920972 | C44: 40974792 | D44: =SUM(D36:D43) -> 39401269 | E44: 30.28 | G44: Gesamtergebnis | H44: =SUM(H36:H43) -> 30244627 | I44: =SUM(I36:I43) -> 31348092 | J44: =SUM(J36:J43) -> 30242580 | K44: 19.61 | M44: Bei der FW wurde Verpackungsschwund und Mischkosten, reduzierte Palettenpreise | Q44: Gesamt | R44: 25365400
M45: mit 8% in Abzug gebracht
A46: Anmerkung für 2021 | G46: Anmerkung für 2020 | Q46: Anmerkung für 2018:
A47: Bei der FW wurde Verpackungsschwund und Mischkosten, reduzierte Palettenpreise | G47: Bei der FW wurde Verpackungsschwund und Mischkosten, reduzierte Palettenpreise | Q47: Bei der FW wurde Verpackungsschwund und Mischkosten, reduzierte Palettenpreise mit 8% in Abzug gebracht.
A48: mit 8% in Abzug gebracht | G48: mit 8% in Abzug gebracht
